llm_confidence/__init__.py
llm_confidence/logprobs_handler.py
llm_confidence-0.2.3.dist-info/LICENSE
llm_confidence-0.2.3.dist-info/METADATA
llm_confidence-0.2.3.dist-info/WHEEL
llm_confidence-0.2.3.dist-info/top_level.txt
llm_confidence-0.2.3.dist-info/RECORD
